Workbook
Name aporte: SIMULADOR!$D$18
Name qtd_anos: SIMULADOR!$D$19
Name rendimento_carteira: SIMULADOR!$D$13
Name taxa_mensal: SIMULADOR!$D$20

Sheet SIMULADOR
B11: Configurações
B12: Salário | D12: 1100
B13: Rendimento Carteira | D13: 0.0089
B14: Porcentagem de investimento | D14: 0.3
B15: Sugestão de Investimento | D15: =$D$12*$D$14 -> 330
A17: 2 | B17: Investimento Mensal
A18: 5 | B18: Quanto Investir por Mês? | D18: 330
A19: 10 | B19: Por Quantos Anos? | D19: 5
A20: 20 | B20: Taxa de Rendimento Mensal? | D20: 0.01079
A21: 30 | B21: Patrimônio Acumulado? | D21: =FV(taxa_mensal,qtd_anos*12,aporte*-1) -> 27646.382
B22: Dividendos Mensais? | D22: =D21*rendimento_carteira -> 246.0528
B24: Cenários | D24: Dividendos
B25: Quanto em 2 anos? | C25: =FV(taxa_mensal,$A17*12,aporte*-1) -> 8985.117 | D25: =$C25*rendimento_carteira -> 79.967541
B26: Quanto em 5 anos? | C26: =FV(taxa_mensal,$A18*12,aporte*-1) -> 27646.382 | D26: =$C26*rendimento_carteira -> 246.0528
B27: Quanto em 10 anos? | C27: =FV(taxa_mensal,$A19*12,aporte*-1) -> 80283.79 | D27: =$C27*rendimento_carteira -> 714.52573
B28: Quanto em 20 anos? | C28: =FV(taxa_mensal,$A20*12,aporte*-1) -> 371315.47 | D28: =$C28*rendimento_carteira -> 3304.7077
B29: Quanto em 30 anos? | C29: =FV(taxa_mensal,$A21*12,aporte*-1) -> 1426316 | D29: =$C29*rendimento_carteira -> 12694.212
B31: PERFIL | C31: Conservador
B32: VALOR A SER INVESTIDO POR MÊS | C32: =aporte -> 330
B34: TIPO DE FII | C34: PERCENTUAL SUGERIDO | D34: VALORES
B35: PAPEL | C35: =VLOOKUP($C$31&"-"&B35,referencia!A2:D20,4,FALSE) -> 0.3 | D35: =$C$32*C35 -> 99
B36: TIJOLO | C36: =VLOOKUP($C$31&"-"&B36,referencia!A3:D21,4,FALSE) -> 0.5 | D36: =$C$32*C36 -> 165
B37: HÍBRIDOS | C37: =VLOOKUP($C$31&"-"&B37,referencia!A4:D22,4,FALSE) -> 0.1 | D37: =$C$32*C37 -> 33
B38: FOFs | C38: =VLOOKUP($C$31&"-"&B38,referencia!A5:D23,4,FALSE) -> 0.1 | D38: =$C$32*C38 -> 33
B39: DESENVOLVIMENTO | C39: =VLOOKUP($C$31&"-"&B39,referencia!A6:D24,4,FALSE) -> 0 | D39: =$C$32*C39 -> 0
B40: HOTELARIA | C40: =VLOOKUP($C$31&"-"&B40,referencia!A7:D25,4,FALSE) -> 0 | D40: =$C$32*C40 -> 0

Sheet referencia
A2: Chave | B2: PERFIL | C2: TIPO DE FII | D2: %
A3: =B3&"-"&C3 -> Conservador-PAPEL | B3: Conservador | C3: PAPEL | D3: 0.3
A4: =B4&"-"&C4 -> Conservador-TIJOLO | B4: Conservador | C4: TIJOLO | D4: 0.5
A5: =B5&"-"&C5 -> Conservador-HÍBRIDOS | B5: Conservador | C5: HÍBRIDOS | D5: 0.1
A6: =B6&"-"&C6 -> Conservador-FOFs | B6: Conservador | C6: FOFs | D6: 0.1
A7: =B7&"-"&C7 -> Conservador-DESENVOLVIMENTO | B7: Conservador | C7: DESENVOLVIMENTO | D7: 0
A8: =B8&"-"&C8 -> Conservador-HOTELARIA | B8: Conservador | C8: HOTELARIA | D8: 0
A9: =B9&"-"&C9 -> Moderado-PAPEL | B9: Moderado | C9: PAPEL | D9: 0.32
A10: =B10&"-"&C10 -> Moderado-TIJOLO | B10: Moderado | C10: TIJOLO | D10: 0.35
A11: =B11&"-"&C11 -> Moderado-HÍBRIDOS | B11: Moderado | C11: HÍBRIDOS | D11: 0.08
A12: =B12&"-"&C12 -> Moderado-FOFs | B12: Moderado | C12: FOFs | D12: 0.05
A13: =B13&"-"&C13 -> Moderado-DESENVOLVIMENTO | B13: Moderado | C13: DESENVOLVIMENTO | D13: 0.1
A14: =B14&"-"&C14 -> Moderado-HOTELARIA | B14: Moderado | C14: HOTELARIA | D14: 0.1
... A20: =B20&"-"&C20 -> Agressivo-HOTELARIA | B20: Agressivo | C20: HOTELARIA | D20: 0.1
